downvocab/__init__.py
downvocab/__main__.py
downvocab-0.0.3.dist-info/METADATA
downvocab-0.0.3.dist-info/WHEEL
downvocab-0.0.3.dist-info/entry_points.txt
downvocab-0.0.3.dist-info/top_level.txt
downvocab-0.0.3.dist-info/RECORD
