Metadata-Version: 2.1
Name: downvocab
Version: 0.0.3
Summary: Download English words
Home-page: https://github.com/takliu/downvocab
Author: Tak Liu
Author-email: liutak999@gmail.com
License: MIT
Platform: UNKNOWN
Classifier: License :: OSI Approved :: MIT License
Classifier: Programming Language :: Python :: 3
Classifier: Programming Language :: Python :: 3.8
Requires-Dist: gTTS (==2.2.3)
